Workbook

Sheet 🏠 Inicio
B2: 💸 DETECTOR DE FUGAS — Control de Gastos Hormiga
B3: Sistema de detección y eliminación de gastos invisibles | Versión 1.0
B5: 1️⃣ CONFIGURA | D5: 2️⃣ REGISTRA | F5: 3️⃣ DESCUBRE
B6: Hoja ⚙️ Config Escribe tu nombre, mes y presupuesto mensual | D6: Hoja 📋 Gastos Diarios Anota cada gasto (chico o grande) al momento de hacerlo | F6: Hoja 🔍 Detector Hormiga Ve exactamente qué categorías se están comiendo tu dinero
B9: 📂 HOJAS DE ESTE SISTEMA
B10: ⚙️ Config | C10: Parámetros personales: nombre, mes, categorías y presupuesto
B11: 📋 Gastos Diarios | C11: Aquí capturas cada gasto — la única hoja que llenas manualmente
B12: 🔍 Detector Hormiga | C12: Ranking automático de tus fugas. Solo lee, no escribas aquí
B13: 📊 Resumen Mensual | C13: Panorama completo: ¿quedaste bien o te fuiste de feria?
B14: 🎯 Plan de Rescate | C14: Calcula cuánto te ahorrará eliminar cada categoría hormiga
B16: 🔒 Tus datos no salen de este archivo. No hay conexión a internet, no hay suscripción. Es tuyo.

Sheet ⚙️ Config
B2: ⚙️ CONFIGURACIÓN PERSONAL
B3: Llena las celdas en azul. No modifiques las grises.
B5: 👤 DATOS PERSONALES
B6: Tu nombre o apodo | C6: Mi nombre
B7: Mes que estás analizando | C7: Enero 2025
B8: Ingreso mensual neto ($) | C8: 15000
B9: Meta de ahorro mensual ($) | C9: 2000
B11: 🏷️ CATEGORÍAS DE GASTO (puedes renombrarlas)
B12: Código | C12: Nombre de categoría | D12: Presupuesto mensual ($) | E12: Color sugerido
B13: CAT01 | C13: Cafeterías y bebidas | D13: 800 | E13: ☕
B14: CAT02 | C14: Comida rápida / antojitos | D14: 1000 | E14: 🌮
B15: CAT03 | C15: Cigarros / vapeadores | D15: 500 | E15: 🚬
B16: CAT04 | C16: Apps y suscripciones | D16: 400 | E16: 📱
B17: CAT05 | C17: Snacks y dulcerías | D17: 350 | E17: 🍬
B18: CAT06 | C18: Taxis y rides extra | D18: 600 | E18: 🚗
B19: CAT07 | C19: Compras de impulso online | D19: 700 | E19: 🛒
B20: CAT08 | C20: Farmacia y salud menor | D20: 300 | E20: 💊
B21: CAT09 | C21: Entretenimiento y ocio | D21: 800 | E21: 🎮
B22: CAT10 | C22: Otros gastos pequeños | D22: 500 | E22: 💸
C23: TOTAL PRESUPUESTADO EN CATEGORÍAS | D23: =SUM(D13:D22) -> 5950

Sheet 📋 Gastos Diarios
A1: 📋 REGISTRO DE GASTOS DIARIOS — Solo llena las columnas en azul
A2: ✏️ Agrega un renglón por cada gasto. Fecha, descripción, monto y categoría. Las demás columnas se llenan solas.
A3: 📅 Fecha | B3: 📝 Descripción del gasto | C3: 🏷️ Categoría | D3: 💵 Monto ($) | E3: 📌 Es hormiga? | F3: 💬 Nota (opcional)
A4: 2025-01-02 | B4: Café en Starbucks camino al trabajo | C4: Cafeterías y bebidas | D4: 85 | E4: =IF(D4="","",IF(AND(D4>0,D4<200),"🐜 SÍ","⬜ No")) -> 🐜 SÍ
A5: 2025-01-02 | B5: Uber del gym a casa | C5: Taxis y rides extra | D5: 65 | E5: =IF(D5="","",IF(AND(D5>0,D5<200),"🐜 SÍ","⬜ No")) -> 🐜 SÍ
A6: 2025-01-03 | B6: OXXO — agua y papas | C6: Snacks y dulcerías | D6: 42 | E6: =IF(D6="","",IF(AND(D6>0,D6<200),"🐜 SÍ","⬜ No")) -> 🐜 SÍ
A7: 2025-01-03 | B7: Netflix mensualidad | C7: Apps y suscripciones | D7: 299 | E7: =IF(D7="","",IF(AND(D7>0,D7<200),"🐜 SÍ","⬜ No")) -> ⬜ No
A8: 2025-01-04 | B8: Tacos en el puesto de la esquina | C8: Comida rápida / antojitos | D8: 90 | E8: =IF(D8="","",IF(AND(D8>0,D8<200),"🐜 SÍ","⬜ No")) -> 🐜 SÍ
A9: 2025-01-05 | B9: Café de la oficina (máquina) | C9: Cafeterías y bebidas | D9: 25 | E9: =IF(D9="","",IF(AND(D9>0,D9<200),"🐜 SÍ","⬜ No")) -> 🐜 SÍ
A10: 2025-01-06 | B10: Amazon — cable que no necesitaba | C10: Compras de impulso online | D10: 189 | E10: =IF(D10="","",IF(AND(D10>0,D10<200),"🐜 SÍ","⬜ No")) -> 🐜 SÍ
A11: 2025-01-07 | B11: Farmacia — vitaminas | C11: Farmacia y salud menor | D11: 145 | E11: =IF(D11="","",IF(AND(D11>0,D11<200),"🐜 SÍ","⬜ No")) -> 🐜 SÍ
A12: 2025-01-08 | B12: Disney+ mensualidad | C12: Apps y suscripciones | D12: 159 | E12: =IF(D12="","",IF(AND(D12>0,D12<200),"🐜 SÍ","⬜ No")) -> 🐜 SÍ
A13: 2025-01-09 | B13: Cigarros | C13: Cigarros / vapeadores | D13: 80 | E13: =IF(D13="","",IF(AND(D13>0,D13<200),"🐜 SÍ","⬜ No")) -> 🐜 SÍ
A14: 2025-01-10 | B14: Lunch en centro comercial | C14: Comida rápida / antojitos | D14: 135 | E14: =IF(D14="","",IF(AND(D14>0,D14<200),"🐜 SÍ","⬜ No")) -> 🐜 SÍ
A15: 2025-01-11 | B15: Spotify | C15: Apps y suscripciones | D15: 99 | E15: =IF(D15="","",IF(AND(D15>0,D15<200),"🐜 SÍ","⬜ No")) -> 🐜 SÍ
... A18: 2025-01-14 | B18: Juego móvil (coins) | C18: Entretenimiento y ocio | D18: 49 | E18: =IF(D18="","",IF(AND(D18>0,D18<200),"🐜 SÍ","⬜ No")) -> 🐜 SÍ
E19: =IF(D19="","",IF(AND(D19>0,D19<200),"🐜 SÍ","⬜ No"))
E20: =IF(D20="","",IF(AND(D20>0,D20<200),"🐜 SÍ","⬜ No"))
E21: =IF(D21="","",IF(AND(D21>0,D21<200),"🐜 SÍ","⬜ No"))
E22: =IF(D22="","",IF(AND(D22>0,D22<200),"🐜 SÍ","⬜ No"))
E23: =IF(D23="","",IF(AND(D23>0,D23<200),"🐜 SÍ","⬜ No"))
E24: =IF(D24="","",IF(AND(D24>0,D24<200),"🐜 SÍ","⬜ No"))
E25: =IF(D25="","",IF(AND(D25>0,D25<200),"🐜 SÍ","⬜ No"))
E26: =IF(D26="","",IF(AND(D26>0,D26<200),"🐜 SÍ","⬜ No"))
E27: =IF(D27="","",IF(AND(D27>0,D27<200),"🐜 SÍ","⬜ No"))
E28: =IF(D28="","",IF(AND(D28>0,D28<200),"🐜 SÍ","⬜ No"))
E29: =IF(D29="","",IF(AND(D29>0,D29<200),"🐜 SÍ","⬜ No"))
E30: =IF(D30="","",IF(AND(D30>0,D30<200),"🐜 SÍ","⬜ No"))
... E63: =IF(D63="","",IF(AND(D63>0,D63<200),"🐜 SÍ","⬜ No"))
A64: TOTAL REGISTRADO | D64: =SUM(D4:D63) -> 1722 | E64: =COUNTIF(E4:E63,"🐜 SÍ")&" gastos hormiga detectados" -> 13 gastos hormiga detectados

Sheet 🔍 Detector Hormiga
B2: 🔍 DETECTOR DE FUGAS — ¿A dónde se fue tu dinero?
B3: Esta hoja se actualiza sola. No escribas aquí — solo lee.
B5: 📊 RESUMEN DEL MES
B6: 💰 Ingreso mensual | G6: ='⚙️ Config'!C8 -> 15000
B7: 💸 Total gastado este mes | G7: ='📋 Gastos Diarios'!D64 -> 1722
B8: 🐜 Total en gastos hormiga | G8: =SUMIF('📋 Gastos Diarios'!E4:E63,"🐜 SÍ",'📋 Gastos Diarios'!D4:D63) -> 1203
B9: 📉 % del ingreso en hormiga | G9: =IF('⚙️ Config'!C8=0,0,G8/'⚙️ Config'!C8) -> 0.0802
B10: 🎯 Meta de ahorro | G10: ='⚙️ Config'!C9 -> 2000
B11: ✅ ¿Lograste la meta? | G11: =IF('⚙️ Config'!C8-G7>='⚙️ Config'!C9,"✅ SÍ","❌ No aún") -> ✅ SÍ
B14: 🏆 RANKING DE CATEGORÍAS (de mayor a menor gasto)
B15: Categoría | C15: Gastado ($) | D15: Presupuesto ($) | E15: Diferencia ($) | F15: % del total | G15: Estado
B16: ='⚙️ Config'!C13 -> Cafeterías y bebidas | C16: =SUMIF('📋 Gastos Diarios'!C4:C63,'⚙️ Config'!C13,'📋 Gastos Diarios'!D4:D63) -> 150 | D16: ='⚙️ Config'!D13 -> 800 | E16: =D16-C16 -> 650 | F16: =IF(G7=0,0,C16/G7) -> 0.087108014 | G16: =IF(C16=0,"⬜ Sin gastos",IF(C16>D16,"🔴 Excedido","✅ OK")) -> ✅ OK
B17: ='⚙️ Config'!C14 -> Comida rápida / antojitos | C17: =SUMIF('📋 Gastos Diarios'!C4:C63,'⚙️ Config'!C14,'📋 Gastos Diarios'!D4:D63) -> 445 | D17: ='⚙️ Config'!D14 -> 1000 | E17: =D17-C17 -> 555 | F17: =IF(G7=0,0,C17/G7) -> 0.25842044 | G17: =IF(C17=0,"⬜ Sin gastos",IF(C17>D17,"🔴 Excedido","✅ OK")) -> ✅ OK
B18: ='⚙️ Config'!C15 -> Cigarros / vapeadores | C18: =SUMIF('📋 Gastos Diarios'!C4:C63,'⚙️ Config'!C15,'📋 Gastos Diarios'!D4:D63) -> 80 | D18: ='⚙️ Config'!D15 -> 500 | E18: =D18-C18 -> 420 | F18: =IF(G7=0,0,C18/G7) -> 0.046457607 | G18: =IF(C18=0,"⬜ Sin gastos",IF(C18>D18,"🔴 Excedido","✅ OK")) -> ✅ OK
B19: ='⚙️ Config'!C16 -> Apps y suscripciones | C19: =SUMIF('📋 Gastos Diarios'!C4:C63,'⚙️ Config'!C16,'📋 Gastos Diarios'!D4:D63) -> 557 | D19: ='⚙️ Config'!D16 -> 400 | E19: =D19-C19 -> -157 | F19: =IF(G7=0,0,C19/G7) -> 0.32346109 | G19: =IF(C19=0,"⬜ Sin gastos",IF(C19>D19,"🔴 Excedido","✅ OK")) -> 🔴 Excedido
B20: ='⚙️ Config'!C17 -> Snacks y dulcerías | C20: =SUMIF('📋 Gastos Diarios'!C4:C63,'⚙️ Config'!C17,'📋 Gastos Diarios'!D4:D63) -> 42 | D20: ='⚙️ Config'!D17 -> 350 | E20: =D20-C20 -> 308 | F20: =IF(G7=0,0,C20/G7) -> 0.024390244 | G20: =IF(C20=0,"⬜ Sin gastos",IF(C20>D20,"🔴 Excedido","✅ OK")) -> ✅ OK
B21: ='⚙️ Config'!C18 -> Taxis y rides extra | C21: =SUMIF('📋 Gastos Diarios'!C4:C63,'⚙️ Config'!C18,'📋 Gastos Diarios'!D4:D63) -> 65 | D21: ='⚙️ Config'!D18 -> 600 | E21: =D21-C21 -> 535 | F21: =IF(G7=0,0,C21/G7) -> 0.037746806 | G21: =IF(C21=0,"⬜ Sin gastos",IF(C21>D21,"🔴 Excedido","✅ OK")) -> ✅ OK
B22: ='⚙️ Config'!C19 -> Compras de impulso online | C22: =SUMIF('📋 Gastos Diarios'!C4:C63,'⚙️ Config'!C19,'📋 Gastos Diarios'!D4:D63) -> 189 | D22: ='⚙️ Config'!D19 -> 700 | E22: =D22-C22 -> 511 | F22: =IF(G7=0,0,C22/G7) -> 0.1097561 | G22: =IF(C22=0,"⬜ Sin gastos",IF(C22>D22,"🔴 Excedido","✅ OK")) -> ✅ OK
B23: ='⚙️ Config'!C20 -> Farmacia y salud menor | C23: =SUMIF('📋 Gastos Diarios'!C4:C63,'⚙️ Config'!C20,'📋 Gastos Diarios'!D4:D63) -> 145 | D23: ='⚙️ Config'!D20 -> 300 | E23: =D23-C23 -> 155 | F23: =IF(G7=0,0,C23/G7) -> 0.084204413 | G23: =IF(C23=0,"⬜ Sin gastos",IF(C23>D23,"🔴 Excedido","✅ OK")) -> ✅ OK
B24: ='⚙️ Config'!C21 -> Entretenimiento y ocio | C24: =SUMIF('📋 Gastos Diarios'!C4:C63,'⚙️ Config'!C21,'📋 Gastos Diarios'!D4:D63) -> 49 | D24: ='⚙️ Config'!D21 -> 800 | E24: =D24-C24 -> 751 | F24: =IF(G7=0,0,C24/G7) -> 0.028455285 | G24: =IF(C24=0,"⬜ Sin gastos",IF(C24>D24,"🔴 Excedido","✅ OK")) -> ✅ OK
B25: ='⚙️ Config'!C22 -> Otros gastos pequeños | C25: =SUMIF('📋 Gastos Diarios'!C4:C63,'⚙️ Config'!C22,'📋 Gastos Diarios'!D4:D63) -> 0 | D25: ='⚙️ Config'!D22 -> 500 | E25: =D25-C25 -> 500 | F25: =IF(G7=0,0,C25/G7) -> 0 | G25: =IF(C25=0,"⬜ Sin gastos",IF(C25>D25,"🔴 Excedido","✅ OK")) -> ⬜ Sin gastos
B26: TOTAL | C26: =SUM(C16:C25) -> 1722 | D26: =SUM(D16:D25) -> 5950

Sheet 📊 Resumen Mensual
B2: 📊 RESUMEN MENSUAL — El panorama completo
B4: 💰 FLUJO DEL MES
B5: Ingreso neto mensual | C5: ='⚙️ Config'!C8 -> 15000
B6: Total gastado | C6: ='📋 Gastos Diarios'!D64 -> 1722
B7: Total en gastos hormiga | C7: =SUMIF('📋 Gastos Diarios'!E4:E63,"🐜 SÍ",'📋 Gastos Diarios'!D4:D63) -> 1203
B8: Saldo al final del mes | C8: ='⚙️ Config'!C8-'📋 Gastos Diarios'!D64 -> 13278
B9: Meta de ahorro | C9: ='⚙️ Config'!C9 -> 2000
B10: Diferencia vs meta | C10: ='⚙️ Config'!C8-'📋 Gastos Diarios'!D64-'⚙️ Config'!C9 -> 11278
B13: 🏷️ GASTO POR CATEGORÍA (automático desde Detector)
B14: Categoría | C14: Gastado | D14: Presupuesto | E14: % Uso | F14: Alerta
B15: ='🔍 Detector Hormiga'!B16 -> Cafeterías y bebidas | C15: ='🔍 Detector Hormiga'!C16 -> 150 | D15: ='🔍 Detector Hormiga'!D16 -> 800 | E15: =IF(D15=0,0,C15/D15) -> 0.1875 | F15: =IF(C15=0,"—",IF(C15/MAX(D15,1)>=1,"🔴 EXCEDIDO",IF(C15/MAX(D15,1)>=0.8,"🟡 Cuidado","🟢 Bien"))) -> 🟢 Bien
B16: ='🔍 Detector Hormiga'!B17 -> Comida rápida / antojitos | C16: ='🔍 Detector Hormiga'!C17 -> 445 | D16: ='🔍 Detector Hormiga'!D17 -> 1000 | E16: =IF(D16=0,0,C16/D16) -> 0.445 | F16: =IF(C16=0,"—",IF(C16/MAX(D16,1)>=1,"🔴 EXCEDIDO",IF(C16/MAX(D16,1)>=0.8,"🟡 Cuidado","🟢 Bien"))) -> 🟢 Bien
B17: ='🔍 Detector Hormiga'!B18 -> Cigarros / vapeadores | C17: ='🔍 Detector Hormiga'!C18 -> 80 | D17: ='🔍 Detector Hormiga'!D18 -> 500 | E17: =IF(D17=0,0,C17/D17) -> 0.16 | F17: =IF(C17=0,"—",IF(C17/MAX(D17,1)>=1,"🔴 EXCEDIDO",IF(C17/MAX(D17,1)>=0.8,"🟡 Cuidado","🟢 Bien"))) -> 🟢 Bien
B18: ='🔍 Detector Hormiga'!B19 -> Apps y suscripciones | C18: ='🔍 Detector Hormiga'!C19 -> 557 | D18: ='🔍 Detector Hormiga'!D19 -> 400 | E18: =IF(D18=0,0,C18/D18) -> 1.3925 | F18: =IF(C18=0,"—",IF(C18/MAX(D18,1)>=1,"🔴 EXCEDIDO",IF(C18/MAX(D18,1)>=0.8,"🟡 Cuidado","🟢 Bien"))) -> 🔴 EXCEDIDO
B19: ='🔍 Detector Hormiga'!B20 -> Snacks y dulcerías | C19: ='🔍 Detector Hormiga'!C20 -> 42 | D19: ='🔍 Detector Hormiga'!D20 -> 350 | E19: =IF(D19=0,0,C19/D19) -> 0.12 | F19: =IF(C19=0,"—",IF(C19/MAX(D19,1)>=1,"🔴 EXCEDIDO",IF(C19/MAX(D19,1)>=0.8,"🟡 Cuidado","🟢 Bien"))) -> 🟢 Bien
B20: ='🔍 Detector Hormiga'!B21 -> Taxis y rides extra | C20: ='🔍 Detector Hormiga'!C21 -> 65 | D20: ='🔍 Detector Hormiga'!D21 -> 600 | E20: =IF(D20=0,0,C20/D20) -> 0.10833333 | F20: =IF(C20=0,"—",IF(C20/MAX(D20,1)>=1,"🔴 EXCEDIDO",IF(C20/MAX(D20,1)>=0.8,"🟡 Cuidado","🟢 Bien"))) -> 🟢 Bien
B21: ='🔍 Detector Hormiga'!B22 -> Compras de impulso online | C21: ='🔍 Detector Hormiga'!C22 -> 189 | D21: ='🔍 Detector Hormiga'!D22 -> 700 | E21: =IF(D21=0,0,C21/D21) -> 0.27 | F21: =IF(C21=0,"—",IF(C21/MAX(D21,1)>=1,"🔴 EXCEDIDO",IF(C21/MAX(D21,1)>=0.8,"🟡 Cuidado","🟢 Bien"))) -> 🟢 Bien
B22: ='🔍 Detector Hormiga'!B23 -> Farmacia y salud menor | C22: ='🔍 Detector Hormiga'!C23 -> 145 | D22: ='🔍 Detector Hormiga'!D23 -> 300 | E22: =IF(D22=0,0,C22/D22) -> 0.48333333 | F22: =IF(C22=0,"—",IF(C22/MAX(D22,1)>=1,"🔴 EXCEDIDO",IF(C22/MAX(D22,1)>=0.8,"🟡 Cuidado","🟢 Bien"))) -> 🟢 Bien
B23: ='🔍 Detector Hormiga'!B24 -> Entretenimiento y ocio | C23: ='🔍 Detector Hormiga'!C24 -> 49 | D23: ='🔍 Detector Hormiga'!D24 -> 800 | E23: =IF(D23=0,0,C23/D23) -> 0.06125 | F23: =IF(C23=0,"—",IF(C23/MAX(D23,1)>=1,"🔴 EXCEDIDO",IF(C23/MAX(D23,1)>=0.8,"🟡 Cuidado","🟢 Bien"))) -> 🟢 Bien
B24: ='🔍 Detector Hormiga'!B25 -> Otros gastos pequeños | C24: ='🔍 Detector Hormiga'!C25 -> 0 | D24: ='🔍 Detector Hormiga'!D25 -> 500 | E24: =IF(D24=0,0,C24/D24) -> 0 | F24: =IF(C24=0,"—",IF(C24/MAX(D24,1)>=1,"🔴 EXCEDIDO",IF(C24/MAX(D24,1)>=0.8,"🟡 Cuidado","🟢 Bien"))) -> —

Sheet 🎯 Plan de Rescate
B2: 🎯 PLAN DE RESCATE — Cuánto puedes recuperar
B3: Indica qué % quieres reducir en cada categoría y verás cuánto dinero recuperas al mes y al año.
B5: Categoría | C5: Gastado este mes | D5: % que vas a reducir | E5: Ahorro mensual | F5: Ahorro anual | G5: ¿Vale la pena? | H5: Compromiso
B6: Cafeterías y bebidas | C6: ='🔍 Detector Hormiga'!C16 -> 150 | D6: 0.2 | E6: =C6*D6 -> 30 | F6: =E6*12 -> 360 | G6: =IF(E6=0,"Sin gasto","⬇️ Reducir "&TEXT(D6,"0%")&" = "&TEXT(E6,"$#,##0")&"/mes") -> ⬇️ Reducir 20% = $30/mes | H6: Escribe aquí tu compromiso
B7: Comida rápida / antojitos | C7: ='🔍 Detector Hormiga'!C17 -> 445 | D7: 0.2 | E7: =C7*D7 -> 89 | F7: =E7*12 -> 1068 | G7: =IF(E7=0,"Sin gasto","⬇️ Reducir "&TEXT(D7,"0%")&" = "&TEXT(E7,"$#,##0")&"/mes") -> ⬇️ Reducir 20% = $89/mes | H7: Escribe aquí tu compromiso
B8: Cigarros / vapeadores | C8: ='🔍 Detector Hormiga'!C18 -> 80 | D8: 0.2 | E8: =C8*D8 -> 16 | F8: =E8*12 -> 192 | G8: =IF(E8=0,"Sin gasto","⬇️ Reducir "&TEXT(D8,"0%")&" = "&TEXT(E8,"$#,##0")&"/mes") -> ⬇️ Reducir 20% = $16/mes | H8: Escribe aquí tu compromiso
B9: Apps y suscripciones | C9: ='🔍 Detector Hormiga'!C19 -> 557 | D9: 0.2 | E9: =C9*D9 -> 111.4 | F9: =E9*12 -> 1336.8 | G9: =IF(E9=0,"Sin gasto","⬇️ Reducir "&TEXT(D9,"0%")&" = "&TEXT(E9,"$#,##0")&"/mes") -> ⬇️ Reducir 20% = $111/mes | H9: Escribe aquí tu compromiso
B10: Snacks y dulcerías | C10: ='🔍 Detector Hormiga'!C20 -> 42 | D10: 0.2 | E10: =C10*D10 -> 8.4 | F10: =E10*12 -> 100.8 | G10: =IF(E10=0,"Sin gasto","⬇️ Reducir "&TEXT(D10,"0%")&" = "&TEXT(E10,"$#,##0")&"/mes") -> ⬇️ Reducir 20% = $8/mes | H10: Escribe aquí tu compromiso
B11: Taxis y rides extra | C11: ='🔍 Detector Hormiga'!C21 -> 65 | D11: 0.2 | E11: =C11*D11 -> 13 | F11: =E11*12 -> 156 | G11: =IF(E11=0,"Sin gasto","⬇️ Reducir "&TEXT(D11,"0%")&" = "&TEXT(E11,"$#,##0")&"/mes") -> ⬇️ Reducir 20% = $13/mes | H11: Escribe aquí tu compromiso
B12: Compras de impulso online | C12: ='🔍 Detector Hormiga'!C22 -> 189 | D12: 0.2 | E12: =C12*D12 -> 37.8 | F12: =E12*12 -> 453.6 | G12: =IF(E12=0,"Sin gasto","⬇️ Reducir "&TEXT(D12,"0%")&" = "&TEXT(E12,"$#,##0")&"/mes") -> ⬇️ Reducir 20% = $38/mes | H12: Escribe aquí tu compromiso
B13: Farmacia y salud menor | C13: ='🔍 Detector Hormiga'!C23 -> 145 | D13: 0.2 | E13: =C13*D13 -> 29 | F13: =E13*12 -> 348 | G13: =IF(E13=0,"Sin gasto","⬇️ Reducir "&TEXT(D13,"0%")&" = "&TEXT(E13,"$#,##0")&"/mes") -> ⬇️ Reducir 20% = $29/mes | H13: Escribe aquí tu compromiso
B14: Entretenimiento y ocio | C14: ='🔍 Detector Hormiga'!C24 -> 49 | D14: 0.2 | E14: =C14*D14 -> 9.8 | F14: =E14*12 -> 117.6 | G14: =IF(E14=0,"Sin gasto","⬇️ Reducir "&TEXT(D14,"0%")&" = "&TEXT(E14,"$#,##0")&"/mes") -> ⬇️ Reducir 20% = $10/mes | H14: Escribe aquí tu compromiso
B15: Otros gastos pequeños | C15: ='🔍 Detector Hormiga'!C25 -> 0 | D15: 0.2 | E15: =C15*D15 -> 0 | F15: =E15*12 -> 0 | G15: =IF(E15=0,"Sin gasto","⬇️ Reducir "&TEXT(D15,"0%")&" = "&TEXT(E15,"$#,##0")&"/mes") -> Sin gasto | H15: Escribe aquí tu compromiso
B16: 🏆 TOTAL RECUPERABLE | C16: =SUM(C6:C15) -> 1722 | E16: =SUM(E6:E15) -> 344.4 | F16: =SUM(F6:F15) -> 4132.8
B18: =IF(F16>0,"💡 Si eliminas estos gastos hormiga, en un año podrías tener $"&TEXT(F16,"#,##0")&" MXN extra. Eso es más que "&TEXT(F16/12,"$#,##0")&" al mes.","Llena la hoja de gastos para ver el cálculo.") -> 💡 Si eliminas estos gastos hormiga, en un año podrías tener $4,133 MXN extra. Eso es más que $344 al mes.
