Workbook

Sheet 🏠 Inicio
B2: 💸 DETECTOR DE FUGAS — Control de Gastos Hormiga
B3: Sistema de detección y eliminación de gastos invisibles | Versión 5.0
B5: 1️⃣ CONFIGURA | D5: 2️⃣ REGISTRA | F5: 3️⃣ DESCUBRE
B6: Hoja ⚙️ Config Escribe tu nombre, mes y presupuesto mensual | D6: Hoja 📋 Gastos Diarios Anota cada gasto (chico o grande) al momento de hacerlo | F6: Hoja 🔍 Detector Hormiga Ve exactamente qué categorías se están comiendo tu dinero Hoja 🎯 Plan de Rescate Calcula cuánto recuperas eliminando cada categoría
B9: 📂 HOJAS DE ESTE SISTEMA
B10: ⚙️ Config | C10: Parámetros personales: nombre, mes, categorías y presupuesto
B11: 📋 Gastos Diarios | C11: Aquí capturas cada gasto — la única hoja que llenas manualmente
B12: 🔍 Detector Hormiga | C12: Ranking automático de tus fugas. Solo lee, no escribas aquí
B13: 📊 Resumen Mensual | C13: Panorama completo: ¿quedaste bien o te fuiste de feria?
B14: 🎯 Plan de Rescate | C14: Calcula cuánto recuperas al reducir cada gasto hormiga
B16: 🔒 Tus datos no salen de este archivo. No hay conexión a internet, no hay suscripción. Es tuyo.
B18: ✏️ QUÉ PUEDES MODIFICAR — Y QUÉ NO
B20: ✅ PUEDES EDITAR:
B21: • ⚙️ Config | C21: Nombre, mes, ingreso, meta de ahorro, nombres de categorías y presupuestos
B22: • 📋 Gastos Diarios | C22: Columnas A (Fecha), B (Descripción), C (Categoría), D (Monto) y E (Nota)
B23: • 🎯 Plan de Rescate | C23: Columna "% que vas a reducir" y la columna de compromisos
B25: 🔒 NO MODIFIQUES:
B26: • 📋 Gastos Diarios | C26: Solo la columna F (¿Es hormiga?) tiene fórmula — no la borres
B27: • 🔍 Detector Hormiga | C27: Hoja de solo lectura — no escribas nada aquí
B28: • 📊 Resumen Mensual | C28: Hoja de solo lectura — se llena sola
B29: • ⚙️ Config | C29: No borres las filas ni cambies los códigos CAT01–CAT15 de la columna B
B31: 🗑️ LIMPIAR EL MES: | C31: En Gastos Diarios → selecciona A4:E93 → presiona Supr (Delete)

Sheet ⚙️ Config
B2: ⚙️ CONFIGURACIÓN PERSONAL
B3: Llena las celdas en azul. No modifiques las grises.
B5: 👤 DATOS PERSONALES
B6: Tu nombre o apodo | C6: Mi nombre
B7: Mes que estás analizando | C7: 45658
B8: Ingreso mensual neto ($) | C8: 18000
B9: Meta de ahorro mensual ($) | C9: 2000
B11: 🏷️ CATEGORÍAS DE GASTO (puedes renombrarlas y asignar su presupuesto)
B12: Código | C12: Nombre de categoría | D12: Presupuesto mensual ($) | E12: Color sugerido
B13: CAT01 | C13: Cafeterías y bebidas | D13: 400 | E13: ☕
B14: CAT02 | C14: Comida rápida y antojitos | D14: 1000 | E14: 🌮
B15: CAT03 | C15: Supermercado y despensa | D15: 4000 | E15: 🛒
B16: CAT04 | C16: Transporte (taxi, valet, casetas) | D16: 200 | E16: 🚗
B17: CAT05 | C17: Apps y suscripciones | D17: 200 | E17: 📱
B18: CAT06 | C18: Snacks y dulcerías | D18: 350 | E18: 🍬
B19: CAT07 | C19: Compras de impulso online | D19: 500 | E19: 📦
B20: CAT08 | C20: Farmacia y salud | D20: 0 | E20: 💊
B21: CAT09 | C21: Entretenimiento y ocio | D21: 1000 | E21: 🎮
B22: CAT10 | C22: Otros gastos | D22: 1500 | E22: 💸
B23: CAT11 | C23: Servicios (luz, agua, internet) | D23: 1150 | E23: 💡
B24: CAT12 | C24: Créditos y mensualidades | D24: 2500 | E24: 💳
... B27: CAT15 | C27: Renta y alquiler | D27: 2000 | E27: 🏠
C28: TOTAL PRESUPUESTADO EN CATEGORÍAS | D28: =SUM(D13:D27) -> 14800

Sheet 📋 Gastos Diarios
A1: 📋 REGISTRO DE GASTOS DIARIOS — Solo llena las columnas en azul
A2: ✏️ Agrega un renglón por cada gasto — columnas A, B, C y D. Las demás se llenan solas. | 🗑️ Para limpiar el mes: selecciona A4:F93 → presiona Supr (Delete)
A3: 📅 Fecha | B3: 📝 Descripción del gasto | C3: 🏷️ Categoría | D3: 💵 Monto ($) | E3: 💬 Nota (opcional) | F3: 📌 Es hormiga?
A4: 45658 | B4: Renta enero | C4: Renta y alquiler | D4: 3500 | F4: =IF(D4="","",IF(AND(D4>0,D4<200),"SÍ","No")) -> No
A5: 45659 | B5: Café en Starbucks camino al trabajo | C5: Cafeterías y bebidas | D5: 85 | F5: =IF(D5="","",IF(AND(D5>0,D5<200),"SÍ","No")) -> SÍ
A6: 45659 | B6: Uber del gym a casa | C6: Transporte (taxi, valet, casetas) | D6: 65 | F6: =IF(D6="","",IF(AND(D6>0,D6<200),"SÍ","No")) -> SÍ
A7: 45660 | B7: OXXO — agua y papas | C7: Snacks y dulcerías | D7: 42 | F7: =IF(D7="","",IF(AND(D7>0,D7<200),"SÍ","No")) -> SÍ
A8: 45660 | B8: Netflix mensualidad | C8: Apps y suscripciones | D8: 299 | F8: =IF(D8="","",IF(AND(D8>0,D8<200),"SÍ","No")) -> No
A9: 45661 | B9: Tacos en el puesto de la esquina | C9: Comida rápida y antojitos | D9: 90 | F9: =IF(D9="","",IF(AND(D9>0,D9<200),"SÍ","No")) -> SÍ
A10: 45662 | B10: Café de la oficina (máquina) | C10: Cafeterías y bebidas | D10: 25 | F10: =IF(D10="","",IF(AND(D10>0,D10<200),"SÍ","No")) -> SÍ
A11: 45662 | B11: Despensa semanal | C11: Supermercado y despensa | D11: 850 | F11: =IF(D11="","",IF(AND(D11>0,D11<200),"SÍ","No")) -> No
A12: 45663 | B12: Amazon — cable que no necesitaba | C12: Compras de impulso online | D12: 189 | F12: =IF(D12="","",IF(AND(D12>0,D12<200),"SÍ","No")) -> SÍ
A13: 45664 | B13: Farmacia — vitaminas | C13: Farmacia y salud | D13: 145 | F13: =IF(D13="","",IF(AND(D13>0,D13<200),"SÍ","No")) -> SÍ
A14: 45665 | B14: Disney+ mensualidad | C14: Apps y suscripciones | D14: 159 | F14: =IF(D14="","",IF(AND(D14>0,D14<200),"SÍ","No")) -> SÍ
A15: 45667 | B15: Lunch en centro comercial | C15: Comida rápida y antojitos | D15: 135 | F15: =IF(D15="","",IF(AND(D15>0,D15<200),"SÍ","No")) -> SÍ
A16: 45668 | B16: Benson | C16: Cigarros y vapeadores | D16: 105 | F16: =IF(D16="","",IF(AND(D16>0,D16<200),"SÍ","No")) -> SÍ
F17: =IF(D17="","",IF(AND(D17>0,D17<200),"SÍ","No"))
F18: =IF(D18="","",IF(AND(D18>0,D18<200),"SÍ","No"))
F19: =IF(D19="","",IF(AND(D19>0,D19<200),"SÍ","No"))
F20: =IF(D20="","",IF(AND(D20>0,D20<200),"SÍ","No"))
F21: =IF(D21="","",IF(AND(D21>0,D21<200),"SÍ","No"))
F22: =IF(D22="","",IF(AND(D22>0,D22<200),"SÍ","No"))
F23: =IF(D23="","",IF(AND(D23>0,D23<200),"SÍ","No"))
F24: =IF(D24="","",IF(AND(D24>0,D24<200),"SÍ","No"))
F25: =IF(D25="","",IF(AND(D25>0,D25<200),"SÍ","No"))
F26: =IF(D26="","",IF(AND(D26>0,D26<200),"SÍ","No"))
F27: =IF(D27="","",IF(AND(D27>0,D27<200),"SÍ","No"))
F28: =IF(D28="","",IF(AND(D28>0,D28<200),"SÍ","No"))
... F93: =IF(D93="","",IF(AND(D93>0,D93<200),"SÍ","No"))
A94: TOTAL REGISTRADO | D94: =SUM(D4:D93) -> 5689 | F94: =COUNTIF(F4:F93,"SÍ")&" gastos hormiga detectados" -> 10 gastos hormiga detectados

Sheet 🔍 Detector Hormiga
B2: 🔍 DETECTOR DE FUGAS — ¿A dónde se fue tu dinero?
B3: Esta hoja se actualiza sola. No escribas aquí — solo lee.
B5: 📊 RESUMEN DEL MES
B6: 💰 Ingreso mensual | G6: ='⚙️ Config'!C8 -> 18000
B7: 💸 Total gastado este mes | G7: ='📋 Gastos Diarios'!D94 -> 5689
B8: 🐜 Total en gastos hormiga | G8: =SUMIF('📋 Gastos Diarios'!F4:F93,"SÍ",'📋 Gastos Diarios'!D4:D93) -> 1040
B9: 📉 % del ingreso en hormiga | G9: =IF('⚙️ Config'!C8=0,0,G8/'⚙️ Config'!C8) -> 0.057777778
B10: 🎯 Meta de ahorro | G10: ='⚙️ Config'!C9 -> 2000
B11: ✅ ¿Lograste la meta? | G11: =IF('⚙️ Config'!C8-G7>='⚙️ Config'!C9,"SÍ","No aún") -> SÍ
B14: 🏆 RESUMEN POR CATEGORÍA
B15: Categoría | C15: Gastado ($) | D15: Presupuesto ($) | E15: Disponible ($) | F15: % del total | G15: Estado
B16: ='⚙️ Config'!C13 -> Cafeterías y bebidas | C16: =SUMIF('📋 Gastos Diarios'!C4:C93,'⚙️ Config'!C13,'📋 Gastos Diarios'!D4:D93) -> 110 | D16: ='⚙️ Config'!D13 -> 400 | E16: =D16-C16 -> 290 | F16: =IF(G7=0,0,C16/G7) -> 0.01933556 | G16: =IF(C16=0,"Sin gastos",IF(C16>D16,"EXCEDIDO","OK")) -> OK
B17: ='⚙️ Config'!C14 -> Comida rápida y antojitos | C17: =SUMIF('📋 Gastos Diarios'!C4:C93,'⚙️ Config'!C14,'📋 Gastos Diarios'!D4:D93) -> 225 | D17: ='⚙️ Config'!D14 -> 1000 | E17: =D17-C17 -> 775 | F17: =IF(G7=0,0,C17/G7) -> 0.039550009 | G17: =IF(C17=0,"Sin gastos",IF(C17>D17,"EXCEDIDO","OK")) -> OK
B18: ='⚙️ Config'!C15 -> Supermercado y despensa | C18: =SUMIF('📋 Gastos Diarios'!C4:C93,'⚙️ Config'!C15,'📋 Gastos Diarios'!D4:D93) -> 850 | D18: ='⚙️ Config'!D15 -> 4000 | E18: =D18-C18 -> 3150 | F18: =IF(G7=0,0,C18/G7) -> 0.14941114 | G18: =IF(C18=0,"Sin gastos",IF(C18>D18,"EXCEDIDO","OK")) -> OK
B19: ='⚙️ Config'!C16 -> Transporte (taxi, valet, casetas) | C19: =SUMIF('📋 Gastos Diarios'!C4:C93,'⚙️ Config'!C16,'📋 Gastos Diarios'!D4:D93) -> 65 | D19: ='⚙️ Config'!D16 -> 200 | E19: =D19-C19 -> 135 | F19: =IF(G7=0,0,C19/G7) -> 0.011425558 | G19: =IF(C19=0,"Sin gastos",IF(C19>D19,"EXCEDIDO","OK")) -> OK
B20: ='⚙️ Config'!C17 -> Apps y suscripciones | C20: =SUMIF('📋 Gastos Diarios'!C4:C93,'⚙️ Config'!C17,'📋 Gastos Diarios'!D4:D93) -> 458 | D20: ='⚙️ Config'!D17 -> 200 | E20: =D20-C20 -> -258 | F20: =IF(G7=0,0,C20/G7) -> 0.08050624 | G20: =IF(C20=0,"Sin gastos",IF(C20>D20,"EXCEDIDO","OK")) -> EXCEDIDO
B21: ='⚙️ Config'!C18 -> Snacks y dulcerías | C21: =SUMIF('📋 Gastos Diarios'!C4:C93,'⚙️ Config'!C18,'📋 Gastos Diarios'!D4:D93) -> 42 | D21: ='⚙️ Config'!D18 -> 350 | E21: =D21-C21 -> 308 | F21: =IF(G7=0,0,C21/G7) -> 0.0073826683 | G21: =IF(C21=0,"Sin gastos",IF(C21>D21,"EXCEDIDO","OK")) -> OK
B22: ='⚙️ Config'!C19 -> Compras de impulso online | C22: =SUMIF('📋 Gastos Diarios'!C4:C93,'⚙️ Config'!C19,'📋 Gastos Diarios'!D4:D93) -> 189 | D22: ='⚙️ Config'!D19 -> 500 | E22: =D22-C22 -> 311 | F22: =IF(G7=0,0,C22/G7) -> 0.033222007 | G22: =IF(C22=0,"Sin gastos",IF(C22>D22,"EXCEDIDO","OK")) -> OK
B23: ='⚙️ Config'!C20 -> Farmacia y salud | C23: =SUMIF('📋 Gastos Diarios'!C4:C93,'⚙️ Config'!C20,'📋 Gastos Diarios'!D4:D93) -> 145 | D23: ='⚙️ Config'!D20 -> 0 | E23: =D23-C23 -> -145 | F23: =IF(G7=0,0,C23/G7) -> 0.025487783 | G23: =IF(C23=0,"Sin gastos",IF(C23>D23,"EXCEDIDO","OK")) -> EXCEDIDO
B24: ='⚙️ Config'!C21 -> Entretenimiento y ocio | C24: =SUMIF('📋 Gastos Diarios'!C4:C93,'⚙️ Config'!C21,'📋 Gastos Diarios'!D4:D93) -> 0 | D24: ='⚙️ Config'!D21 -> 1000 | E24: =D24-C24 -> 1000 | F24: =IF(G7=0,0,C24/G7) -> 0 | G24: =IF(C24=0,"Sin gastos",IF(C24>D24,"EXCEDIDO","OK")) -> Sin gastos
B25: ='⚙️ Config'!C22 -> Otros gastos | C25: =SUMIF('📋 Gastos Diarios'!C4:C93,'⚙️ Config'!C22,'📋 Gastos Diarios'!D4:D93) -> 0 | D25: ='⚙️ Config'!D22 -> 1500 | E25: =D25-C25 -> 1500 | F25: =IF(G7=0,0,C25/G7) -> 0 | G25: =IF(C25=0,"Sin gastos",IF(C25>D25,"EXCEDIDO","OK")) -> Sin gastos
B26: ='⚙️ Config'!C23 -> Servicios (luz, agua, internet) | C26: =SUMIF('📋 Gastos Diarios'!C4:C93,'⚙️ Config'!C23,'📋 Gastos Diarios'!D4:D93) -> 0 | D26: ='⚙️ Config'!D23 -> 1150 | E26: =D26-C26 -> 1150 | F26: =IF(G7=0,0,C26/G7) -> 0 | G26: =IF(C26=0,"Sin gastos",IF(C26>D26,"EXCEDIDO","OK")) -> Sin gastos
B27: ='⚙️ Config'!C24 -> Créditos y mensualidades | C27: =SUMIF('📋 Gastos Diarios'!C4:C93,'⚙️ Config'!C24,'📋 Gastos Diarios'!D4:D93) -> 0 | D27: ='⚙️ Config'!D24 -> 2500 | E27: =D27-C27 -> 2500 | F27: =IF(G7=0,0,C27/G7) -> 0 | G27: =IF(C27=0,"Sin gastos",IF(C27>D27,"EXCEDIDO","OK")) -> Sin gastos
B28: ='⚙️ Config'!C25 -> Educación y cursos | C28: =SUMIF('📋 Gastos Diarios'!C4:C93,'⚙️ Config'!C25,'📋 Gastos Diarios'!D4:D93) -> 0 | D28: ='⚙️ Config'!D25 -> 0 | E28: =D28-C28 -> 0 | F28: =IF(G7=0,0,C28/G7) -> 0 | G28: =IF(C28=0,"Sin gastos",IF(C28>D28,"EXCEDIDO","OK")) -> Sin gastos
B29: ='⚙️ Config'!C26 -> Cigarros y vapeadores | C29: =SUMIF('📋 Gastos Diarios'!C4:C93,'⚙️ Config'!C26,'📋 Gastos Diarios'!D4:D93) -> 105 | D29: ='⚙️ Config'!D26 -> 0 | E29: =D29-C29 -> -105 | F29: =IF(G7=0,0,C29/G7) -> 0.018456671 | G29: =IF(C29=0,"Sin gastos",IF(C29>D29,"EXCEDIDO","OK")) -> EXCEDIDO
B30: ='⚙️ Config'!C27 -> Renta y alquiler | C30: =SUMIF('📋 Gastos Diarios'!C4:C93,'⚙️ Config'!C27,'📋 Gastos Diarios'!D4:D93) -> 3500 | D30: ='⚙️ Config'!D27 -> 2000 | E30: =D30-C30 -> -1500 | F30: =IF(G7=0,0,C30/G7) -> 0.61522236 | G30: =IF(C30=0,"Sin gastos",IF(C30>D30,"EXCEDIDO","OK")) -> EXCEDIDO
B31: TOTAL | C31: =SUM(C16:C30) -> 5689 | D31: =SUM(D16:D30) -> 14800

Sheet 📊 Resumen Mensual
B2: 📊 RESUMEN MENSUAL — El panorama completo
B4: 💰 FLUJO DEL MES
B5: Ingreso neto mensual | C5: ='⚙️ Config'!C8 -> 18000
B6: Total gastado | C6: ='📋 Gastos Diarios'!D94 -> 5689
B7: Total en gastos hormiga | C7: =SUMIF('📋 Gastos Diarios'!F4:F93,"SÍ",'📋 Gastos Diarios'!D4:D93) -> 1040
B8: Saldo al final del mes | C8: ='⚙️ Config'!C8-'📋 Gastos Diarios'!D94 -> 12311
B9: Meta de ahorro | C9: ='⚙️ Config'!C9 -> 2000
B10: Diferencia vs meta | C10: ='⚙️ Config'!C8-'📋 Gastos Diarios'!D94-'⚙️ Config'!C9 -> 10311
B13: 🏷️ GASTO POR CATEGORÍA (automático desde Detector)
B14: Categoría | C14: Gastado | D14: Presupuesto | E14: % Uso | F14: Alerta
B15: ='🔍 Detector Hormiga'!B16 -> Cafeterías y bebidas | C15: ='🔍 Detector Hormiga'!C16 -> 110 | D15: ='🔍 Detector Hormiga'!D16 -> 400 | E15: =IF(D15=0,0,C15/D15) -> 0.275 | F15: =IF(C15=0,"—",IF(C15/MAX(D15,1)>=1,"EXCEDIDO",IF(C15/MAX(D15,1)>=0.8,"Cuidado","Bien"))) -> Bien
B16: ='🔍 Detector Hormiga'!B17 -> Comida rápida y antojitos | C16: ='🔍 Detector Hormiga'!C17 -> 225 | D16: ='🔍 Detector Hormiga'!D17 -> 1000 | E16: =IF(D16=0,0,C16/D16) -> 0.225 | F16: =IF(C16=0,"—",IF(C16/MAX(D16,1)>=1,"EXCEDIDO",IF(C16/MAX(D16,1)>=0.8,"Cuidado","Bien"))) -> Bien
B17: ='🔍 Detector Hormiga'!B18 -> Supermercado y despensa | C17: ='🔍 Detector Hormiga'!C18 -> 850 | D17: ='🔍 Detector Hormiga'!D18 -> 4000 | E17: =IF(D17=0,0,C17/D17) -> 0.2125 | F17: =IF(C17=0,"—",IF(C17/MAX(D17,1)>=1,"EXCEDIDO",IF(C17/MAX(D17,1)>=0.8,"Cuidado","Bien"))) -> Bien
B18: ='🔍 Detector Hormiga'!B19 -> Transporte (taxi, valet, casetas) | C18: ='🔍 Detector Hormiga'!C19 -> 65 | D18: ='🔍 Detector Hormiga'!D19 -> 200 | E18: =IF(D18=0,0,C18/D18) -> 0.325 | F18: =IF(C18=0,"—",IF(C18/MAX(D18,1)>=1,"EXCEDIDO",IF(C18/MAX(D18,1)>=0.8,"Cuidado","Bien"))) -> Bien
B19: ='🔍 Detector Hormiga'!B20 -> Apps y suscripciones | C19: ='🔍 Detector Hormiga'!C20 -> 458 | D19: ='🔍 Detector Hormiga'!D20 -> 200 | E19: =IF(D19=0,0,C19/D19) -> 2.29 | F19: =IF(C19=0,"—",IF(C19/MAX(D19,1)>=1,"EXCEDIDO",IF(C19/MAX(D19,1)>=0.8,"Cuidado","Bien"))) -> EXCEDIDO
B20: ='🔍 Detector Hormiga'!B21 -> Snacks y dulcerías | C20: ='🔍 Detector Hormiga'!C21 -> 42 | D20: ='🔍 Detector Hormiga'!D21 -> 350 | E20: =IF(D20=0,0,C20/D20) -> 0.12 | F20: =IF(C20=0,"—",IF(C20/MAX(D20,1)>=1,"EXCEDIDO",IF(C20/MAX(D20,1)>=0.8,"Cuidado","Bien"))) -> Bien
B21: ='🔍 Detector Hormiga'!B22 -> Compras de impulso online | C21: ='🔍 Detector Hormiga'!C22 -> 189 | D21: ='🔍 Detector Hormiga'!D22 -> 500 | E21: =IF(D21=0,0,C21/D21) -> 0.378 | F21: =IF(C21=0,"—",IF(C21/MAX(D21,1)>=1,"EXCEDIDO",IF(C21/MAX(D21,1)>=0.8,"Cuidado","Bien"))) -> Bien
B22: ='🔍 Detector Hormiga'!B23 -> Farmacia y salud | C22: ='🔍 Detector Hormiga'!C23 -> 145 | D22: ='🔍 Detector Hormiga'!D23 -> 0 | E22: =IF(D22=0,0,C22/D22) -> 0 | F22: =IF(C22=0,"—",IF(C22/MAX(D22,1)>=1,"EXCEDIDO",IF(C22/MAX(D22,1)>=0.8,"Cuidado","Bien"))) -> EXCEDIDO
B23: ='🔍 Detector Hormiga'!B24 -> Entretenimiento y ocio | C23: ='🔍 Detector Hormiga'!C24 -> 0 | D23: ='🔍 Detector Hormiga'!D24 -> 1000 | E23: =IF(D23=0,0,C23/D23) -> 0 | F23: =IF(C23=0,"—",IF(C23/MAX(D23,1)>=1,"EXCEDIDO",IF(C23/MAX(D23,1)>=0.8,"Cuidado","Bien"))) -> —
B24: ='🔍 Detector Hormiga'!B25 -> Otros gastos | C24: ='🔍 Detector Hormiga'!C25 -> 0 | D24: ='🔍 Detector Hormiga'!D25 -> 1500 | E24: =IF(D24=0,0,C24/D24) -> 0 | F24: =IF(C24=0,"—",IF(C24/MAX(D24,1)>=1,"EXCEDIDO",IF(C24/MAX(D24,1)>=0.8,"Cuidado","Bien"))) -> —
B25: ='🔍 Detector Hormiga'!B26 -> Servicios (luz, agua, internet) | C25: ='🔍 Detector Hormiga'!C26 -> 0 | D25: ='🔍 Detector Hormiga'!D26 -> 1150 | E25: =IF(D25=0,0,C25/D25) -> 0 | F25: =IF(C25=0,"—",IF(C25/MAX(D25,1)>=1,"EXCEDIDO",IF(C25/MAX(D25,1)>=0.8,"Cuidado","Bien"))) -> —
B26: ='🔍 Detector Hormiga'!B27 -> Créditos y mensualidades | C26: ='🔍 Detector Hormiga'!C27 -> 0 | D26: ='🔍 Detector Hormiga'!D27 -> 2500 | E26: =IF(D26=0,0,C26/D26) -> 0 | F26: =IF(C26=0,"—",IF(C26/MAX(D26,1)>=1,"EXCEDIDO",IF(C26/MAX(D26,1)>=0.8,"Cuidado","Bien"))) -> —
... B29: ='🔍 Detector Hormiga'!B30 -> Renta y alquiler | C29: ='🔍 Detector Hormiga'!C30 -> 3500 | D29: ='🔍 Detector Hormiga'!D30 -> 2000 | E29: =IF(D29=0,0,C29/D29) -> 1.75 | F29: =IF(C29=0,"—",IF(C29/MAX(D29,1)>=1,"EXCEDIDO",IF(C29/MAX(D29,1)>=0.8,"Cuidado","Bien"))) -> EXCEDIDO

Sheet 🎯 Plan de Rescate
B2: 🎯 PLAN DE RESCATE — Cuánto puedes recuperar
B3: Indica qué % quieres reducir en cada categoría y verás cuánto dinero recuperas al mes y al año.
B5: Categoría | C5: Gastado este mes | D5: % que vas a reducir | E5: Ahorro mensual | F5: Ahorro anual | G5: ¿Vale la pena? | H5: ✏️ Mi compromiso (escribe aquí)
B6: ='⚙️ Config'!C13 -> Cafeterías y bebidas | C6: ='🔍 Detector Hormiga'!C16 -> 110 | D6: 0.5 | E6: =IF(C6=0,0,C6*VALUE(D6)) -> 55 | F6: =IF(C6=0,0,E6*12) -> 660 | G6: =IF(E6=0,"Sin gasto","⬇️ Reducir "&D6&" = $"&TEXT(E6,"#,##0")&"/mes") -> ⬇️ Reducir 0.5 = $55/mes
B7: ='⚙️ Config'!C14 -> Comida rápida y antojitos | C7: ='🔍 Detector Hormiga'!C17 -> 225 | D7: 20% | E7: =IF(C7=0,0,C7*VALUE(D7)) -> 45 | F7: =IF(C7=0,0,E7*12) -> 540 | G7: =IF(E7=0,"Sin gasto","⬇️ Reducir "&D7&" = $"&TEXT(E7,"#,##0")&"/mes") -> ⬇️ Reducir 20% = $45/mes
B8: ='⚙️ Config'!C15 -> Supermercado y despensa | C8: ='🔍 Detector Hormiga'!C18 -> 850 | D8: 0.5 | E8: =IF(C8=0,0,C8*VALUE(D8)) -> 425 | F8: =IF(C8=0,0,E8*12) -> 5100 | G8: =IF(E8=0,"Sin gasto","⬇️ Reducir "&D8&" = $"&TEXT(E8,"#,##0")&"/mes") -> ⬇️ Reducir 0.5 = $425/mes
B9: ='⚙️ Config'!C16 -> Transporte (taxi, valet, casetas) | C9: ='🔍 Detector Hormiga'!C19 -> 65 | D9: 20% | E9: =IF(C9=0,0,C9*VALUE(D9)) -> 13 | F9: =IF(C9=0,0,E9*12) -> 156 | G9: =IF(E9=0,"Sin gasto","⬇️ Reducir "&D9&" = $"&TEXT(E9,"#,##0")&"/mes") -> ⬇️ Reducir 20% = $13/mes
B10: ='⚙️ Config'!C17 -> Apps y suscripciones | C10: ='🔍 Detector Hormiga'!C20 -> 458 | D10: 20% | E10: =IF(C10=0,0,C10*VALUE(D10)) -> 91.6 | F10: =IF(C10=0,0,E10*12) -> 1099.2 | G10: =IF(E10=0,"Sin gasto","⬇️ Reducir "&D10&" = $"&TEXT(E10,"#,##0")&"/mes") -> ⬇️ Reducir 20% = $92/mes
B11: ='⚙️ Config'!C18 -> Snacks y dulcerías | C11: ='🔍 Detector Hormiga'!C21 -> 42 | D11: 20% | E11: =IF(C11=0,0,C11*VALUE(D11)) -> 8.4 | F11: =IF(C11=0,0,E11*12) -> 100.8 | G11: =IF(E11=0,"Sin gasto","⬇️ Reducir "&D11&" = $"&TEXT(E11,"#,##0")&"/mes") -> ⬇️ Reducir 20% = $8/mes
B12: ='⚙️ Config'!C19 -> Compras de impulso online | C12: ='🔍 Detector Hormiga'!C22 -> 189 | D12: 20% | E12: =IF(C12=0,0,C12*VALUE(D12)) -> 37.8 | F12: =IF(C12=0,0,E12*12) -> 453.6 | G12: =IF(E12=0,"Sin gasto","⬇️ Reducir "&D12&" = $"&TEXT(E12,"#,##0")&"/mes") -> ⬇️ Reducir 20% = $38/mes
B13: ='⚙️ Config'!C20 -> Farmacia y salud | C13: ='🔍 Detector Hormiga'!C23 -> 145 | D13: 20% | E13: =IF(C13=0,0,C13*VALUE(D13)) -> 29 | F13: =IF(C13=0,0,E13*12) -> 348 | G13: =IF(E13=0,"Sin gasto","⬇️ Reducir "&D13&" = $"&TEXT(E13,"#,##0")&"/mes") -> ⬇️ Reducir 20% = $29/mes
B14: ='⚙️ Config'!C21 -> Entretenimiento y ocio | C14: ='🔍 Detector Hormiga'!C24 -> 0 | D14: 20% | E14: =IF(C14=0,0,C14*VALUE(D14)) -> 0 | F14: =IF(C14=0,0,E14*12) -> 0 | G14: =IF(E14=0,"Sin gasto","⬇️ Reducir "&D14&" = $"&TEXT(E14,"#,##0")&"/mes") -> Sin gasto
B15: ='⚙️ Config'!C22 -> Otros gastos | C15: ='🔍 Detector Hormiga'!C25 -> 0 | D15: 20% | E15: =IF(C15=0,0,C15*VALUE(D15)) -> 0 | F15: =IF(C15=0,0,E15*12) -> 0 | G15: =IF(E15=0,"Sin gasto","⬇️ Reducir "&D15&" = $"&TEXT(E15,"#,##0")&"/mes") -> Sin gasto
B16: ='⚙️ Config'!C23 -> Servicios (luz, agua, internet) | C16: ='🔍 Detector Hormiga'!C26 -> 0 | D16: 20% | E16: =IF(C16=0,0,C16*VALUE(D16)) -> 0 | F16: =IF(C16=0,0,E16*12) -> 0 | G16: =IF(E16=0,"Sin gasto","⬇️ Reducir "&D16&" = $"&TEXT(E16,"#,##0")&"/mes") -> Sin gasto
B17: ='⚙️ Config'!C24 -> Créditos y mensualidades | C17: ='🔍 Detector Hormiga'!C27 -> 0 | D17: 20% | E17: =IF(C17=0,0,C17*VALUE(D17)) -> 0 | F17: =IF(C17=0,0,E17*12) -> 0 | G17: =IF(E17=0,"Sin gasto","⬇️ Reducir "&D17&" = $"&TEXT(E17,"#,##0")&"/mes") -> Sin gasto
B18: ='⚙️ Config'!C25 -> Educación y cursos | C18: ='🔍 Detector Hormiga'!C28 -> 0 | D18: 20% | E18: =IF(C18=0,0,C18*VALUE(D18)) -> 0 | F18: =IF(C18=0,0,E18*12) -> 0 | G18: =IF(E18=0,"Sin gasto","⬇️ Reducir "&D18&" = $"&TEXT(E18,"#,##0")&"/mes") -> Sin gasto
B19: ='⚙️ Config'!C26 -> Cigarros y vapeadores | C19: ='🔍 Detector Hormiga'!C29 -> 105 | D19: 20% | E19: =IF(C19=0,0,C19*VALUE(D19)) -> 21 | F19: =IF(C19=0,0,E19*12) -> 252 | G19: =IF(E19=0,"Sin gasto","⬇️ Reducir "&D19&" = $"&TEXT(E19,"#,##0")&"/mes") -> ⬇️ Reducir 20% = $21/mes
B20: ='⚙️ Config'!C27 -> Renta y alquiler | C20: ='🔍 Detector Hormiga'!C30 -> 3500 | D20: 20% | E20: =IF(C20=0,0,C20*VALUE(D20)) -> 700 | F20: =IF(C20=0,0,E20*12) -> 8400 | G20: =IF(E20=0,"Sin gasto","⬇️ Reducir "&D20&" = $"&TEXT(E20,"#,##0")&"/mes") -> ⬇️ Reducir 20% = $700/mes
B21: 🏆 TOTAL RECUPERABLE | C21: =SUM(C6:C20) -> 5689 | E21: =SUM(E6:E20) -> 1425.8 | F21: =SUM(F6:F20) -> 17109.6
B23: =IF(F21>0,"💡 Si reduces estos gastos, en un año podrías tener $"&TEXT(F21,"#,##0")&" MXN extra — más de $"&TEXT(F21/12,"#,##0")&" al mes.","") -> 💡 Si reduces estos gastos, en un año podrías tener $17,110 MXN extra — más de $1,426 al mes.
